README.txt
setup.py
collective/__init__.py
collective.js.colorpicker.egg-info/PKG-INFO
collective.js.colorpicker.egg-info/SOURCES.txt
collective.js.colorpicker.egg-info/dependency_links.txt
collective.js.colorpicker.egg-info/entry_points.txt
collective.js.colorpicker.egg-info/namespace_packages.txt
collective.js.colorpicker.egg-info/not-zip-safe
collective.js.colorpicker.egg-info/requires.txt
collective.js.colorpicker.egg-info/top_level.txt
collective/js/__init__.py
collective/js/colorpicker/__init__.py
collective/js/colorpicker/configure.zcml
collective/js/colorpicker/tests.py
collective/js/colorpicker/version.txt
collective/js/colorpicker/css/colorpicker.css
collective/js/colorpicker/images/Thumbs.db
collective/js/colorpicker/images/blank.gif
collective/js/colorpicker/images/colorpicker_background.png
collective/js/colorpicker/images/colorpicker_hex.png
collective/js/colorpicker/images/colorpicker_hsb_b.png
collective/js/colorpicker/images/colorpicker_hsb_h.png
collective/js/colorpicker/images/colorpicker_hsb_s.png
collective/js/colorpicker/images/colorpicker_indic.gif
collective/js/colorpicker/images/colorpicker_overlay.png
collective/js/colorpicker/images/colorpicker_rgb_b.png
collective/js/colorpicker/images/colorpicker_rgb_g.png
collective/js/colorpicker/images/colorpicker_rgb_r.png
collective/js/colorpicker/images/colorpicker_select.gif
collective/js/colorpicker/images/colorpicker_submit.png
collective/js/colorpicker/images/custom_background.png
collective/js/colorpicker/images/custom_hex.png
collective/js/colorpicker/images/custom_hsb_b.png
collective/js/colorpicker/images/custom_hsb_h.png
collective/js/colorpicker/images/custom_hsb_s.png
collective/js/colorpicker/images/custom_indic.gif
collective/js/colorpicker/images/custom_rgb_b.png
collective/js/colorpicker/images/custom_rgb_g.png
collective/js/colorpicker/images/custom_rgb_r.png
collective/js/colorpicker/images/custom_submit.png
collective/js/colorpicker/images/select.png
collective/js/colorpicker/images/select2.png
collective/js/colorpicker/images/slider.png
collective/js/colorpicker/js/colorpicker.js
collective/js/colorpicker/js/eye.js
collective/js/colorpicker/js/utils.js
collective/js/colorpicker/profiles/default/cssregistry.xml
collective/js/colorpicker/profiles/default/jsregistry.xml
docs/HISTORY.txt
docs/INSTALL.txt
docs/LICENSE.GPL
docs/LICENSE.txt